{
  "timestamp": "2025-10-09T20:45:47.440667+00:00",
  "total_directories": 16,
  "successful": 16,
  "failed": 0,
  "migrations": [
    {
      "timestamp": "2025-10-09T20:45:47.295070+00:00",
      "source": "23_compliance\\shards\\01_identitaet_personen\\policies",
      "target": "23_compliance\\policies\\23_compliance\\01_identitaet_personen",
      "files_copied": [
        "bias_fairness.yaml",
        "evidence_audit.yaml",
        "gdpr_compliance.yaml",
        "hash_only_enforcement.yaml",
        "no_pii_storage.yaml",
        "secrets_management.yaml",
        "versioning_policy.yaml"
      ],
      "status": "success"
    },
    {
      "timestamp": "2025-10-09T20:45:47.304907+00:00",
      "source": "23_compliance\\shards\\02_dokumente_nachweise\\policies",
      "target": "23_compliance\\policies\\23_compliance\\02_dokumente_nachweise",
      "files_copied": [
        "bias_fairness.yaml",
        "evidence_audit.yaml",
        "gdpr_compliance.yaml",
        "hash_only_enforcement.yaml",
        "no_pii_storage.yaml",
        "secrets_management.yaml",
        "versioning_policy.yaml"
      ],
      "status": "success"
    },
    {
      "timestamp": "2025-10-09T20:45:47.313340+00:00",
      "source": "23_compliance\\shards\\03_zugang_berechtigungen\\policies",
      "target": "23_compliance\\policies\\23_compliance\\03_zugang_berechtigungen",
      "files_copied": [
        "bias_fairness.yaml",
        "evidence_audit.yaml",
        "gdpr_compliance.yaml",
        "hash_only_enforcement.yaml",
        "no_pii_storage.yaml",
        "secrets_management.yaml",
        "versioning_policy.yaml"
      ],
      "status": "success"
    },
    {
      "timestamp": "2025-10-09T20:45:47.317587+00:00",
      "source": "23_compliance\\shards\\04_kommunikation_daten\\policies",
      "target": "23_compliance\\policies\\23_compliance\\04_kommunikation_daten",
      "files_copied": [
        "bias_fairness.yaml",
        "evidence_audit.yaml",
        "gdpr_compliance.yaml",
        "hash_only_enforcement.yaml",
        "no_pii_storage.yaml",
        "secrets_management.yaml",
        "versioning_policy.yaml"
      ],
      "status": "success"
    },
    {
      "timestamp": "2025-10-09T20:45:47.330276+00:00",
      "source": "23_compliance\\shards\\05_gesundheit_medizin\\policies",
      "target": "23_compliance\\policies\\23_compliance\\05_gesundheit_medizin",
      "files_copied": [
        "bias_fairness.yaml",
        "evidence_audit.yaml",
        "gdpr_compliance.yaml",
        "hash_only_enforcement.yaml",
        "no_pii_storage.yaml",
        "secrets_management.yaml",
        "versioning_policy.yaml"
      ],
      "status": "success"
    },
    {
      "timestamp": "2025-10-09T20:45:47.340826+00:00",
      "source": "23_compliance\\shards\\06_bildung_qualifikationen\\policies",
      "target": "23_compliance\\policies\\23_compliance\\06_bildung_qualifikationen",
      "files_copied": [
        "bias_fairness.yaml",
        "evidence_audit.yaml",
        "gdpr_compliance.yaml",
        "hash_only_enforcement.yaml",
        "no_pii_storage.yaml",
        "secrets_management.yaml",
        "versioning_policy.yaml"
      ],
      "status": "success"
    },
    {
      "timestamp": "2025-10-09T20:45:47.349168+00:00",
      "source": "23_compliance\\shards\\07_familie_soziales\\policies",
      "target": "23_compliance\\policies\\23_compliance\\07_familie_soziales",
      "files_copied": [
        "bias_fairness.yaml",
        "evidence_audit.yaml",
        "gdpr_compliance.yaml",
        "hash_only_enforcement.yaml",
        "no_pii_storage.yaml",
        "secrets_management.yaml",
        "versioning_policy.yaml"
      ],
      "status": "success"
    },
    {
      "timestamp": "2025-10-09T20:45:47.359548+00:00",
      "source": "23_compliance\\shards\\08_mobilitaet_fahrzeuge\\policies",
      "target": "23_compliance\\policies\\23_compliance\\08_mobilitaet_fahrzeuge",
      "files_copied": [
        "bias_fairness.yaml",
        "evidence_audit.yaml",
        "gdpr_compliance.yaml",
        "hash_only_enforcement.yaml",
        "no_pii_storage.yaml",
        "secrets_management.yaml",
        "versioning_policy.yaml"
      ],
      "status": "success"
    },
    {
      "timestamp": "2025-10-09T20:45:47.370112+00:00",
      "source": "23_compliance\\shards\\09_arbeit_karriere\\policies",
      "target": "23_compliance\\policies\\23_compliance\\09_arbeit_karriere",
      "files_copied": [
        "bias_fairness.yaml",
        "evidence_audit.yaml",
        "gdpr_compliance.yaml",
        "hash_only_enforcement.yaml",
        "no_pii_storage.yaml",
        "secrets_management.yaml",
        "versioning_policy.yaml"
      ],
      "status": "success"
    },
    {
      "timestamp": "2025-10-09T20:45:47.381433+00:00",
      "source": "23_compliance\\shards\\10_finanzen_banking\\policies",
      "target": "23_compliance\\policies\\23_compliance\\10_finanzen_banking",
      "files_copied": [
        "bias_fairness.yaml",
        "evidence_audit.yaml",
        "gdpr_compliance.yaml",
        "hash_only_enforcement.yaml",
        "no_pii_storage.yaml",
        "secrets_management.yaml",
        "versioning_policy.yaml"
      ],
      "status": "success"
    },
    {
      "timestamp": "2025-10-09T20:45:47.391413+00:00",
      "source": "23_compliance\\shards\\11_versicherungen_risiken\\policies",
      "target": "23_compliance\\policies\\23_compliance\\11_versicherungen_risiken",
      "files_copied": [
        "bias_fairness.yaml",
        "evidence_audit.yaml",
        "gdpr_compliance.yaml",
        "hash_only_enforcement.yaml",
        "no_pii_storage.yaml",
        "secrets_management.yaml",
        "versioning_policy.yaml"
      ],
      "status": "success"
    },
    {
      "timestamp": "2025-10-09T20:45:47.393565+00:00",
      "source": "23_compliance\\shards\\12_immobilien_grundstuecke\\policies",
      "target": "23_compliance\\policies\\23_compliance\\12_immobilien_grundstuecke",
      "files_copied": [
        "bias_fairness.yaml",
        "evidence_audit.yaml",
        "gdpr_compliance.yaml",
        "hash_only_enforcement.yaml",
        "no_pii_storage.yaml",
        "secrets_management.yaml",
        "versioning_policy.yaml"
      ],
      "status": "success"
    },
    {
      "timestamp": "2025-10-09T20:45:47.410584+00:00",
      "source": "23_compliance\\shards\\13_unternehmen_gewerbe\\policies",
      "target": "23_compliance\\policies\\23_compliance\\13_unternehmen_gewerbe",
      "files_copied": [
        "bias_fairness.yaml",
        "evidence_audit.yaml",
        "gdpr_compliance.yaml",
        "hash_only_enforcement.yaml",
        "no_pii_storage.yaml",
        "secrets_management.yaml",
        "versioning_policy.yaml"
      ],
      "status": "success"
    },
    {
      "timestamp": "2025-10-09T20:45:47.415180+00:00",
      "source": "23_compliance\\shards\\14_vertraege_vereinbarungen\\policies",
      "target": "23_compliance\\policies\\23_compliance\\14_vertraege_vereinbarungen",
      "files_copied": [
        "bias_fairness.yaml",
        "evidence_audit.yaml",
        "gdpr_compliance.yaml",
        "hash_only_enforcement.yaml",
        "no_pii_storage.yaml",
        "secrets_management.yaml",
        "versioning_policy.yaml"
      ],
      "status": "success"
    },
    {
      "timestamp": "2025-10-09T20:45:47.424893+00:00",
      "source": "23_compliance\\shards\\15_handel_transaktionen\\policies",
      "target": "23_compliance\\policies\\23_compliance\\15_handel_transaktionen",
      "files_copied": [
        "bias_fairness.yaml",
        "evidence_audit.yaml",
        "gdpr_compliance.yaml",
        "hash_only_enforcement.yaml",
        "no_pii_storage.yaml",
        "secrets_management.yaml",
        "versioning_policy.yaml"
      ],
      "status": "success"
    },
    {
      "timestamp": "2025-10-09T20:45:47.440667+00:00",
      "source": "23_compliance\\shards\\16_behoerden_verwaltung\\policies",
      "target": "23_compliance\\policies\\23_compliance\\16_behoerden_verwaltung",
      "files_copied": [
        "bias_fairness.yaml",
        "evidence_audit.yaml",
        "gdpr_compliance.yaml",
        "hash_only_enforcement.yaml",
        "no_pii_storage.yaml",
        "secrets_management.yaml",
        "versioning_policy.yaml"
      ],
      "status": "success"
    }
  ],
  "errors": []
}