{
  "timestamp": "2025-10-24T19:28:27.978071",
  "version": "1.0.0",
  "status": "100% SYNCHRONIZED",
  "artifacts": {
    "sot_contract_expanded_TRUE": {
      "path": "C:\\Users\\bibel\\Documents\\Github\\SSID\\16_codex\\structure\\level3\\sot_contract_expanded_TRUE.yaml",
      "version": "4.0.0",
      "rules": 4896
    },
    "sot_contract_COMPLETE": {
      "path": "C:\\Users\\bibel\\Documents\\Github\\SSID\\16_codex\\contracts\\sot\\sot_contract_COMPLETE.yaml",
      "version": "3.2.0",
      "rules": 31709
    },
    "sot_contract": {
      "path": "C:\\Users\\bibel\\Documents\\Github\\SSID\\16_codex\\contracts\\sot\\sot_contract.yaml",
      "version": "4.0.0",
      "rules": 13942
    },
    "sot_contract_part2": {
      "path": "C:\\Users\\bibel\\Documents\\Github\\SSID\\16_codex\\contracts\\sot\\sot_contract_part2.yaml",
      "version": "unknown",
      "rules": 256
    },
    "sot_contract_part3": {
      "path": "C:\\Users\\bibel\\Documents\\Github\\SSID\\16_codex\\contracts\\sot\\sot_contract_part3.yaml",
      "version": "unknown",
      "rules": 256
    }
  },
  "master_index": {
    "total_rules_all_artifacts": 51059,
    "unique_rules": 51059,
    "duplicates_merged": 0,
    "location": "24_meta_orchestration/registry/sot_master_index.json"
  },
  "shard_system": {
    "total_shards": 384,
    "shards_updated": 384,
    "coverage": "100.0%"
  },
  "synchronization": {
    "method": "Master Index with Full Distribution",
    "consistency": "100% - All shards reference same master index",
    "traceability": "100% - All rules traced to source artifacts"
  }
}